epicsscan/__init__.py
epicsscan/create_scan.py
epicsscan/datafile.py
epicsscan/epics_scandb.py
epicsscan/file_utils.py
epicsscan/macro_kernel.py
epicsscan/macros_init.py
epicsscan/positioner.py
epicsscan/qxafs_monitor.py
epicsscan/saveable.py
epicsscan/scan.py
epicsscan/scandb.py
epicsscan/scandb_schema.py
epicsscan/server.py
epicsscan/simpledb.py
epicsscan/site_config.py
epicsscan/slew_scan.py
epicsscan/slew_scan1d.py
epicsscan/spec_config.py
epicsscan/spec_emulator.py
epicsscan/station_config.py
epicsscan/utils.py
epicsscan/version.py
epicsscan/xafs_scan.py
epicsscan/detectors/__init__.py
epicsscan/detectors/ad_eiger.py
epicsscan/detectors/ad_integrator.py
epicsscan/detectors/ad_mca.py
epicsscan/detectors/ad_perkinelmer.py
epicsscan/detectors/ad_pilatus.py
epicsscan/detectors/areadetector.py
epicsscan/detectors/base.py
epicsscan/detectors/counter.py
epicsscan/detectors/mca.py
epicsscan/detectors/notes.txt
epicsscan/detectors/quadem.py
epicsscan/detectors/scaler.py
epicsscan/detectors/struck.py
epicsscan/detectors/trigger.py
epicsscan/detectors/usbctr.py
epicsscan/detectors/xrd_calibration.py
epicsscan/detectors/xspress3.py
epicsscan/gui/__init__.py
epicsscan/gui/common_commands.py
epicsscan/gui/default_config.ini
epicsscan/gui/edit_detectors.py
epicsscan/gui/edit_extrapvs.py
epicsscan/gui/edit_general.py
epicsscan/gui/edit_macros.py
epicsscan/gui/edit_positioners.py
epicsscan/gui/edit_scandefs.py
epicsscan/gui/edit_sequences.py
epicsscan/gui/gui_utils.py
epicsscan/gui/liveviewerApp.py
epicsscan/gui/pvconnector.py
epicsscan/gui/scanApp.py
epicsscan/gui/scan_panels.py
epicsscan/icons/epics_scan.icns
epicsscan/icons/epics_scan.ico
epicsscan-2026.1.0.dist-info/licenses/LICENSE
epicsscan-2026.1.0.dist-info/METADATA
epicsscan-2026.1.0.dist-info/WHEEL
epicsscan-2026.1.0.dist-info/top_level.txt
epicsscan-2026.1.0.dist-info/RECORD
